{
  "type": "minecraft:crafting_shapeless",

  "group": "wallpaper_rolls",
  "ingredients": [
    {
      "item": "minecraft:paper"
    },
    {
      "item": "minecraft:slime_ball"
    },
    {
      "item": "minecraft:paper"
    },
    {
      "item": "minecraft:paper"
    },
    {
      "item": "dye_depot:amber_dye"
    },
    {
      "item": "minecraft:paper"
    },
    {
      "item": "minecraft:paper"
    },
    {
      "item": "minecraft:paper"
    },
    {
      "item": "minecraft:paper"
    }
  ],
  "result": {
    "item": "wallpapers:amber_wallpaper_roll",
    "count": 14
  },
  "conditions": [
    {
      "type": "forge:mod_loaded",
      "modid": "dye_depot"
    }
  ]
}